[
  {
    "time_utc": "2026-04-21 07:00:24 UTC",
    "total_active": 39,
    "new_added": 0,
    "removed": 0,
    "buffered_ai": 0
  },
  {
    "time_utc": "2026-04-21 06:55:22 UTC",
    "total_active": 39,
    "new_added": 0,
    "removed": 0,
    "buffered_ai": 0
  },
  {
    "time_utc": "2026-04-21 06:50:19 UTC",
    "total_active": 39,
    "new_added": 0,
    "removed": 0,
    "buffered_ai": 0
  },
  {
    "time_utc": "2026-04-21 06:45:25 UTC",
    "total_active": 39,
    "new_added": 0,
    "removed": 0,
    "buffered_ai": 0
  },
  {
    "time_utc": "2026-04-21 06:40:22 UTC",
    "total_active": 39,
    "new_added": 0,
    "removed": 0,
    "buffered_ai": 0
  },
  {
    "time_utc": "2026-04-21 06:35:22 UTC",
    "total_active": 39,
    "new_added": 0,
    "removed": 0,
    "buffered_ai": 0
  },
  {
    "time_utc": "2026-04-21 06:30:30 UTC",
    "total_active": 39,
    "new_added": 0,
    "removed": 0,
    "buffered_ai": 0
  },
  {
    "time_utc": "2026-04-21 06:25:29 UTC",
    "total_active": 39,
    "new_added": 0,
    "removed": 0,
    "buffered_ai": 0
  },
  {
    "time_utc": "2026-04-21 06:20:26 UTC",
    "total_active": 39,
    "new_added": 0,
    "removed": 0,
    "buffered_ai": 0
  },
  {
    "time_utc": "2026-04-21 06:15:20 UTC",
    "total_active": 39,
    "new_added": 0,
    "removed": 0,
    "buffered_ai": 0
  },
  {
    "time_utc": "2026-04-21 06:10:25 UTC",
    "total_active": 39,
    "new_added": 0,
    "removed": 0,
    "buffered_ai": 0
  },
  {
    "time_utc": "2026-04-21 06:05:26 UTC",
    "total_active": 39,
    "new_added": 0,
    "removed": 0,
    "buffered_ai": 0
  },
  {
    "time_utc": "2026-04-21 06:00:25 UTC",
    "total_active": 39,
    "new_added": 0,
    "removed": 0,
    "buffered_ai": 0
  },
  {
    "time_utc": "2026-04-21 05:55:20 UTC",
    "total_active": 39,
    "new_added": 0,
    "removed": 0,
    "buffered_ai": 0
  },
  {
    "time_utc": "2026-04-21 05:50:25 UTC",
    "total_active": 39,
    "new_added": 0,
    "removed": 0,
    "buffered_ai": 0
  },
  {
    "time_utc": "2026-04-21 05:45:25 UTC",
    "total_active": 39,
    "new_added": 0,
    "removed": 0,
    "buffered_ai": 0
  },
  {
    "time_utc": "2026-04-21 05:40:26 UTC",
    "total_active": 39,
    "new_added": 0,
    "removed": 0,
    "buffered_ai": 0
  },
  {
    "time_utc": "2026-04-21 05:35:23 UTC",
    "total_active": 39,
    "new_added": 0,
    "removed": 0,
    "buffered_ai": 0
  },
  {
    "time_utc": "2026-04-21 05:30:24 UTC",
    "total_active": 39,
    "new_added": 0,
    "removed": 0,
    "buffered_ai": 0
  },
  {
    "time_utc": "2026-04-21 05:25:23 UTC",
    "total_active": 39,
    "new_added": 0,
    "removed": 0,
    "buffered_ai": 0
  },
  {
    "time_utc": "2026-04-21 05:20:28 UTC",
    "total_active": 39,
    "new_added": 0,
    "removed": 0,
    "buffered_ai": 0
  },
  {
    "time_utc": "2026-04-21 05:15:19 UTC",
    "total_active": 39,
    "new_added": 0,
    "removed": 0,
    "buffered_ai": 0
  },
  {
    "time_utc": "2026-04-21 05:10:21 UTC",
    "total_active": 39,
    "new_added": 0,
    "removed": 0,
    "buffered_ai": 0
  },
  {
    "time_utc": "2026-04-21 05:05:20 UTC",
    "total_active": 39,
    "new_added": 0,
    "removed": 0,
    "buffered_ai": 0
  },
  {
    "time_utc": "2026-04-21 05:00:23 UTC",
    "total_active": 39,
    "new_added": 0,
    "removed": 0,
    "buffered_ai": 0
  },
  {
    "time_utc": "2026-04-21 04:55:22 UTC",
    "total_active": 39,
    "new_added": 0,
    "removed": 0,
    "buffered_ai": 0
  },
  {
    "time_utc": "2026-04-21 04:50:22 UTC",
    "total_active": 39,
    "new_added": 0,
    "removed": 0,
    "buffered_ai": 0
  },
  {
    "time_utc": "2026-04-21 04:45:23 UTC",
    "total_active": 39,
    "new_added": 0,
    "removed": 0,
    "buffered_ai": 0
  },
  {
    "time_utc": "2026-04-21 04:40:28 UTC",
    "total_active": 39,
    "new_added": 0,
    "removed": 0,
    "buffered_ai": 0
  },
  {
    "time_utc": "2026-04-21 04:35:19 UTC",
    "total_active": 39,
    "new_added": 0,
    "removed": 0,
    "buffered_ai": 0
  },
  {
    "time_utc": "2026-04-21 04:30:25 UTC",
    "total_active": 39,
    "new_added": 0,
    "removed": 0,
    "buffered_ai": 0
  },
  {
    "time_utc": "2026-04-21 04:25:19 UTC",
    "total_active": 39,
    "new_added": 0,
    "removed": 0,
    "buffered_ai": 0
  },
  {
    "time_utc": "2026-04-21 04:20:26 UTC",
    "total_active": 39,
    "new_added": 0,
    "removed": 0,
    "buffered_ai": 0
  },
  {
    "time_utc": "2026-04-21 04:15:25 UTC",
    "total_active": 39,
    "new_added": 0,
    "removed": 0,
    "buffered_ai": 0
  },
  {
    "time_utc": "2026-04-21 04:10:22 UTC",
    "total_active": 39,
    "new_added": 0,
    "removed": 0,
    "buffered_ai": 0
  },
  {
    "time_utc": "2026-04-21 04:05:19 UTC",
    "total_active": 39,
    "new_added": 0,
    "removed": 0,
    "buffered_ai": 0
  },
  {
    "time_utc": "2026-04-21 04:00:21 UTC",
    "total_active": 39,
    "new_added": 0,
    "removed": 0,
    "buffered_ai": 0
  },
  {
    "time_utc": "2026-04-21 03:55:21 UTC",
    "total_active": 39,
    "new_added": 0,
    "removed": 0,
    "buffered_ai": 0
  },
  {
    "time_utc": "2026-04-21 03:50:23 UTC",
    "total_active": 39,
    "new_added": 0,
    "removed": 0,
    "buffered_ai": 0
  },
  {
    "time_utc": "2026-04-21 03:45:20 UTC",
    "total_active": 39,
    "new_added": 0,
    "removed": 0,
    "buffered_ai": 0
  },
  {
    "time_utc": "2026-04-21 03:40:18 UTC",
    "total_active": 39,
    "new_added": 0,
    "removed": 0,
    "buffered_ai": 0
  },
  {
    "time_utc": "2026-04-21 03:35:22 UTC",
    "total_active": 39,
    "new_added": 0,
    "removed": 0,
    "buffered_ai": 0
  },
  {
    "time_utc": "2026-04-21 03:30:20 UTC",
    "total_active": 39,
    "new_added": 0,
    "removed": 0,
    "buffered_ai": 0
  },
  {
    "time_utc": "2026-04-21 03:25:24 UTC",
    "total_active": 39,
    "new_added": 0,
    "removed": 0,
    "buffered_ai": 0
  },
  {
    "time_utc": "2026-04-21 03:20:22 UTC",
    "total_active": 39,
    "new_added": 0,
    "removed": 0,
    "buffered_ai": 0
  },
  {
    "time_utc": "2026-04-21 03:15:24 UTC",
    "total_active": 39,
    "new_added": 0,
    "removed": 0,
    "buffered_ai": 0
  },
  {
    "time_utc": "2026-04-21 03:10:21 UTC",
    "total_active": 39,
    "new_added": 0,
    "removed": 0,
    "buffered_ai": 0
  },
  {
    "time_utc": "2026-04-21 03:05:18 UTC",
    "total_active": 39,
    "new_added": 0,
    "removed": 0,
    "buffered_ai": 0
  },
  {
    "time_utc": "2026-04-21 03:00:28 UTC",
    "total_active": 39,
    "new_added": 0,
    "removed": 0,
    "buffered_ai": 0
  },
  {
    "time_utc": "2026-04-21 02:55:21 UTC",
    "total_active": 39,
    "new_added": 0,
    "removed": 0,
    "buffered_ai": 0
  },
  {
    "time_utc": "2026-04-21 02:50:19 UTC",
    "total_active": 39,
    "new_added": 0,
    "removed": 0,
    "buffered_ai": 0
  },
  {
    "time_utc": "2026-04-21 02:45:20 UTC",
    "total_active": 39,
    "new_added": 0,
    "removed": 0,
    "buffered_ai": 0
  },
  {
    "time_utc": "2026-04-21 02:40:21 UTC",
    "total_active": 39,
    "new_added": 0,
    "removed": 0,
    "buffered_ai": 0
  },
  {
    "time_utc": "2026-04-21 02:35:17 UTC",
    "total_active": 39,
    "new_added": 0,
    "removed": 0,
    "buffered_ai": 0
  },
  {
    "time_utc": "2026-04-21 02:30:19 UTC",
    "total_active": 39,
    "new_added": 0,
    "removed": 0,
    "buffered_ai": 0
  },
  {
    "time_utc": "2026-04-21 02:25:18 UTC",
    "total_active": 39,
    "new_added": 0,
    "removed": 0,
    "buffered_ai": 0
  },
  {
    "time_utc": "2026-04-21 02:20:20 UTC",
    "total_active": 39,
    "new_added": 0,
    "removed": 0,
    "buffered_ai": 0
  },
  {
    "time_utc": "2026-04-21 02:15:28 UTC",
    "total_active": 39,
    "new_added": 0,
    "removed": 0,
    "buffered_ai": 0
  },
  {
    "time_utc": "2026-04-21 02:10:23 UTC",
    "total_active": 39,
    "new_added": 0,
    "removed": 0,
    "buffered_ai": 0
  },
  {
    "time_utc": "2026-04-21 02:05:19 UTC",
    "total_active": 39,
    "new_added": 0,
    "removed": 0,
    "buffered_ai": 0
  },
  {
    "time_utc": "2026-04-21 02:00:29 UTC",
    "total_active": 39,
    "new_added": 0,
    "removed": 0,
    "buffered_ai": 0
  },
  {
    "time_utc": "2026-04-21 01:55:25 UTC",
    "total_active": 39,
    "new_added": 0,
    "removed": 0,
    "buffered_ai": 0
  },
  {
    "time_utc": "2026-04-21 01:50:18 UTC",
    "total_active": 39,
    "new_added": 0,
    "removed": 0,
    "buffered_ai": 0
  },
  {
    "time_utc": "2026-04-21 01:45:20 UTC",
    "total_active": 39,
    "new_added": 0,
    "removed": 0,
    "buffered_ai": 0
  },
  {
    "time_utc": "2026-04-21 01:40:20 UTC",
    "total_active": 39,
    "new_added": 0,
    "removed": 0,
    "buffered_ai": 0
  },
  {
    "time_utc": "2026-04-21 01:35:28 UTC",
    "total_active": 39,
    "new_added": 0,
    "removed": 0,
    "buffered_ai": 0
  },
  {
    "time_utc": "2026-04-21 01:30:20 UTC",
    "total_active": 39,
    "new_added": 0,
    "removed": 0,
    "buffered_ai": 0
  },
  {
    "time_utc": "2026-04-21 01:25:20 UTC",
    "total_active": 39,
    "new_added": 0,
    "removed": 0,
    "buffered_ai": 0
  },
  {
    "time_utc": "2026-04-21 01:20:23 UTC",
    "total_active": 39,
    "new_added": 0,
    "removed": 0,
    "buffered_ai": 0
  },
  {
    "time_utc": "2026-04-21 01:15:27 UTC",
    "total_active": 39,
    "new_added": 0,
    "removed": 0,
    "buffered_ai": 0
  },
  {
    "time_utc": "2026-04-21 01:10:23 UTC",
    "total_active": 39,
    "new_added": 0,
    "removed": 0,
    "buffered_ai": 0
  },
  {
    "time_utc": "2026-04-21 01:05:19 UTC",
    "total_active": 39,
    "new_added": 0,
    "removed": 0,
    "buffered_ai": 0
  },
  {
    "time_utc": "2026-04-21 01:00:26 UTC",
    "total_active": 39,
    "new_added": 0,
    "removed": 0,
    "buffered_ai": 0
  },
  {
    "time_utc": "2026-04-21 00:55:22 UTC",
    "total_active": 39,
    "new_added": 0,
    "removed": 0,
    "buffered_ai": 0
  },
  {
    "time_utc": "2026-04-21 00:50:17 UTC",
    "total_active": 39,
    "new_added": 0,
    "removed": 0,
    "buffered_ai": 0
  },
  {
    "time_utc": "2026-04-21 00:45:20 UTC",
    "total_active": 39,
    "new_added": 0,
    "removed": 0,
    "buffered_ai": 0
  },
  {
    "time_utc": "2026-04-21 00:40:18 UTC",
    "total_active": 39,
    "new_added": 0,
    "removed": 0,
    "buffered_ai": 0
  },
  {
    "time_utc": "2026-04-21 00:35:21 UTC",
    "total_active": 39,
    "new_added": 0,
    "removed": 0,
    "buffered_ai": 0
  },
  {
    "time_utc": "2026-04-21 00:30:28 UTC",
    "total_active": 39,
    "new_added": 0,
    "removed": 0,
    "buffered_ai": 0
  },
  {
    "time_utc": "2026-04-21 00:25:19 UTC",
    "total_active": 39,
    "new_added": 0,
    "removed": 0,
    "buffered_ai": 0
  },
  {
    "time_utc": "2026-04-21 00:20:21 UTC",
    "total_active": 39,
    "new_added": 0,
    "removed": 0,
    "buffered_ai": 0
  },
  {
    "time_utc": "2026-04-21 00:15:22 UTC",
    "total_active": 39,
    "new_added": 0,
    "removed": 0,
    "buffered_ai": 0
  },
  {
    "time_utc": "2026-04-21 00:10:21 UTC",
    "total_active": 39,
    "new_added": 0,
    "removed": 0,
    "buffered_ai": 0
  },
  {
    "time_utc": "2026-04-21 00:05:18 UTC",
    "total_active": 39,
    "new_added": 0,
    "removed": 0,
    "buffered_ai": 0
  },
  {
    "time_utc": "2026-04-21 00:00:24 UTC",
    "total_active": 39,
    "new_added": 0,
    "removed": 0,
    "buffered_ai": 0
  },
  {
    "time_utc": "2026-04-20 23:55:21 UTC",
    "total_active": 39,
    "new_added": 0,
    "removed": 0,
    "buffered_ai": 0
  },
  {
    "time_utc": "2026-04-20 23:50:21 UTC",
    "total_active": 39,
    "new_added": 0,
    "removed": 0,
    "buffered_ai": 0
  },
  {
    "time_utc": "2026-04-20 23:45:20 UTC",
    "total_active": 39,
    "new_added": 0,
    "removed": 0,
    "buffered_ai": 0
  },
  {
    "time_utc": "2026-04-20 23:40:21 UTC",
    "total_active": 39,
    "new_added": 0,
    "removed": 0,
    "buffered_ai": 0
  },
  {
    "time_utc": "2026-04-20 23:35:21 UTC",
    "total_active": 39,
    "new_added": 0,
    "removed": 0,
    "buffered_ai": 0
  },
  {
    "time_utc": "2026-04-20 23:30:23 UTC",
    "total_active": 39,
    "new_added": 0,
    "removed": 0,
    "buffered_ai": 0
  },
  {
    "time_utc": "2026-04-20 23:25:22 UTC",
    "total_active": 39,
    "new_added": 0,
    "removed": 0,
    "buffered_ai": 0
  },
  {
    "time_utc": "2026-04-20 23:20:23 UTC",
    "total_active": 39,
    "new_added": 0,
    "removed": 0,
    "buffered_ai": 0
  },
  {
    "time_utc": "2026-04-20 23:15:18 UTC",
    "total_active": 39,
    "new_added": 0,
    "removed": 0,
    "buffered_ai": 0
  },
  {
    "time_utc": "2026-04-20 23:10:20 UTC",
    "total_active": 39,
    "new_added": 0,
    "removed": 0,
    "buffered_ai": 0
  },
  {
    "time_utc": "2026-04-20 23:05:23 UTC",
    "total_active": 39,
    "new_added": 0,
    "removed": 0,
    "buffered_ai": 0
  },
  {
    "time_utc": "2026-04-20 23:00:32 UTC",
    "total_active": 39,
    "new_added": 0,
    "removed": 0,
    "buffered_ai": 0
  },
  {
    "time_utc": "2026-04-20 22:55:27 UTC",
    "total_active": 39,
    "new_added": 0,
    "removed": 0,
    "buffered_ai": 0
  },
  {
    "time_utc": "2026-04-20 22:50:17 UTC",
    "total_active": 39,
    "new_added": 0,
    "removed": 0,
    "buffered_ai": 0
  },
  {
    "time_utc": "2026-04-20 22:45:20 UTC",
    "total_active": 39,
    "new_added": 0,
    "removed": 0,
    "buffered_ai": 0
  },
  {
    "time_utc": "2026-04-20 22:40:21 UTC",
    "total_active": 39,
    "new_added": 0,
    "removed": 0,
    "buffered_ai": 0
  },
  {
    "time_utc": "2026-04-20 22:35:19 UTC",
    "total_active": 39,
    "new_added": 0,
    "removed": 0,
    "buffered_ai": 0
  },
  {
    "time_utc": "2026-04-20 22:30:22 UTC",
    "total_active": 39,
    "new_added": 0,
    "removed": 0,
    "buffered_ai": 0
  },
  {
    "time_utc": "2026-04-20 22:25:23 UTC",
    "total_active": 39,
    "new_added": 0,
    "removed": 0,
    "buffered_ai": 0
  },
  {
    "time_utc": "2026-04-20 22:20:22 UTC",
    "total_active": 39,
    "new_added": 0,
    "removed": 0,
    "buffered_ai": 0
  },
  {
    "time_utc": "2026-04-20 22:15:21 UTC",
    "total_active": 39,
    "new_added": 0,
    "removed": 0,
    "buffered_ai": 0
  },
  {
    "time_utc": "2026-04-20 22:10:27 UTC",
    "total_active": 39,
    "new_added": 0,
    "removed": 0,
    "buffered_ai": 0
  },
  {
    "time_utc": "2026-04-20 22:05:19 UTC",
    "total_active": 39,
    "new_added": 0,
    "removed": 0,
    "buffered_ai": 0
  },
  {
    "time_utc": "2026-04-20 22:00:26 UTC",
    "total_active": 39,
    "new_added": 0,
    "removed": 0,
    "buffered_ai": 0
  },
  {
    "time_utc": "2026-04-20 21:55:21 UTC",
    "total_active": 39,
    "new_added": 0,
    "removed": 0,
    "buffered_ai": 0
  },
  {
    "time_utc": "2026-04-20 21:50:23 UTC",
    "total_active": 39,
    "new_added": 0,
    "removed": 0,
    "buffered_ai": 0
  },
  {
    "time_utc": "2026-04-20 21:45:20 UTC",
    "total_active": 39,
    "new_added": 0,
    "removed": 0,
    "buffered_ai": 0
  },
  {
    "time_utc": "2026-04-20 21:40:25 UTC",
    "total_active": 39,
    "new_added": 0,
    "removed": 0,
    "buffered_ai": 0
  },
  {
    "time_utc": "2026-04-20 21:35:17 UTC",
    "total_active": 39,
    "new_added": 0,
    "removed": 0,
    "buffered_ai": 0
  },
  {
    "time_utc": "2026-04-20 21:30:24 UTC",
    "total_active": 39,
    "new_added": 0,
    "removed": 0,
    "buffered_ai": 0
  },
  {
    "time_utc": "2026-04-20 21:25:20 UTC",
    "total_active": 39,
    "new_added": 0,
    "removed": 0,
    "buffered_ai": 0
  },
  {
    "time_utc": "2026-04-20 21:20:21 UTC",
    "total_active": 39,
    "new_added": 0,
    "removed": 0,
    "buffered_ai": 0
  },
  {
    "time_utc": "2026-04-20 21:15:21 UTC",
    "total_active": 39,
    "new_added": 0,
    "removed": 0,
    "buffered_ai": 0
  },
  {
    "time_utc": "2026-04-20 21:10:23 UTC",
    "total_active": 39,
    "new_added": 0,
    "removed": 0,
    "buffered_ai": 0
  },
  {
    "time_utc": "2026-04-20 21:05:20 UTC",
    "total_active": 39,
    "new_added": 0,
    "removed": 0,
    "buffered_ai": 0
  },
  {
    "time_utc": "2026-04-20 21:00:29 UTC",
    "total_active": 39,
    "new_added": 0,
    "removed": 0,
    "buffered_ai": 0
  },
  {
    "time_utc": "2026-04-20 20:55:25 UTC",
    "total_active": 39,
    "new_added": 0,
    "removed": 0,
    "buffered_ai": 0
  },
  {
    "time_utc": "2026-04-20 20:50:20 UTC",
    "total_active": 39,
    "new_added": 0,
    "removed": 0,
    "buffered_ai": 0
  },
  {
    "time_utc": "2026-04-20 20:45:27 UTC",
    "total_active": 39,
    "new_added": 0,
    "removed": 0,
    "buffered_ai": 0
  },
  {
    "time_utc": "2026-04-20 20:40:21 UTC",
    "total_active": 39,
    "new_added": 0,
    "removed": 0,
    "buffered_ai": 0
  },
  {
    "time_utc": "2026-04-20 20:35:19 UTC",
    "total_active": 39,
    "new_added": 0,
    "removed": 0,
    "buffered_ai": 0
  },
  {
    "time_utc": "2026-04-20 20:30:21 UTC",
    "total_active": 39,
    "new_added": 0,
    "removed": 0,
    "buffered_ai": 0
  },
  {
    "time_utc": "2026-04-20 20:25:18 UTC",
    "total_active": 39,
    "new_added": 0,
    "removed": 0,
    "buffered_ai": 0
  },
  {
    "time_utc": "2026-04-20 20:20:20 UTC",
    "total_active": 39,
    "new_added": 0,
    "removed": 0,
    "buffered_ai": 0
  },
  {
    "time_utc": "2026-04-20 20:15:23 UTC",
    "total_active": 39,
    "new_added": 0,
    "removed": 0,
    "buffered_ai": 0
  },
  {
    "time_utc": "2026-04-20 20:10:29 UTC",
    "total_active": 39,
    "new_added": 0,
    "removed": 0,
    "buffered_ai": 0
  },
  {
    "time_utc": "2026-04-20 20:05:21 UTC",
    "total_active": 39,
    "new_added": 0,
    "removed": 0,
    "buffered_ai": 0
  },
  {
    "time_utc": "2026-04-20 20:00:32 UTC",
    "total_active": 39,
    "new_added": 0,
    "removed": 0,
    "buffered_ai": 0
  },
  {
    "time_utc": "2026-04-20 19:55:23 UTC",
    "total_active": 39,
    "new_added": 0,
    "removed": 0,
    "buffered_ai": 0
  },
  {
    "time_utc": "2026-04-20 19:50:27 UTC",
    "total_active": 39,
    "new_added": 0,
    "removed": 0,
    "buffered_ai": 0
  },
  {
    "time_utc": "2026-04-20 19:45:19 UTC",
    "total_active": 39,
    "new_added": 0,
    "removed": 0,
    "buffered_ai": 0
  },
  {
    "time_utc": "2026-04-20 19:40:26 UTC",
    "total_active": 39,
    "new_added": 0,
    "removed": 0,
    "buffered_ai": 0
  },
  {
    "time_utc": "2026-04-20 19:35:24 UTC",
    "total_active": 39,
    "new_added": 0,
    "removed": 0,
    "buffered_ai": 0
  },
  {
    "time_utc": "2026-04-20 19:30:21 UTC",
    "total_active": 39,
    "new_added": 0,
    "removed": 0,
    "buffered_ai": 0
  },
  {
    "time_utc": "2026-04-20 19:25:25 UTC",
    "total_active": 39,
    "new_added": 0,
    "removed": 0,
    "buffered_ai": 0
  },
  {
    "time_utc": "2026-04-20 19:20:24 UTC",
    "total_active": 39,
    "new_added": 0,
    "removed": 0,
    "buffered_ai": 0
  },
  {
    "time_utc": "2026-04-20 19:15:22 UTC",
    "total_active": 39,
    "new_added": 0,
    "removed": 0,
    "buffered_ai": 0
  },
  {
    "time_utc": "2026-04-20 19:10:21 UTC",
    "total_active": 39,
    "new_added": 0,
    "removed": 0,
    "buffered_ai": 0
  },
  {
    "time_utc": "2026-04-20 19:05:24 UTC",
    "total_active": 39,
    "new_added": 0,
    "removed": 0,
    "buffered_ai": 0
  },
  {
    "time_utc": "2026-04-20 19:00:26 UTC",
    "total_active": 39,
    "new_added": 0,
    "removed": 0,
    "buffered_ai": 0
  },
  {
    "time_utc": "2026-04-20 18:55:25 UTC",
    "total_active": 39,
    "new_added": 0,
    "removed": 0,
    "buffered_ai": 0
  },
  {
    "time_utc": "2026-04-20 18:50:19 UTC",
    "total_active": 39,
    "new_added": 0,
    "removed": 0,
    "buffered_ai": 0
  },
  {
    "time_utc": "2026-04-20 18:45:26 UTC",
    "total_active": 39,
    "new_added": 0,
    "removed": 0,
    "buffered_ai": 0
  },
  {
    "time_utc": "2026-04-20 18:40:21 UTC",
    "total_active": 39,
    "new_added": 0,
    "removed": 0,
    "buffered_ai": 0
  },
  {
    "time_utc": "2026-04-20 18:35:33 UTC",
    "total_active": 39,
    "new_added": 0,
    "removed": 0,
    "buffered_ai": 0
  },
  {
    "time_utc": "2026-04-20 18:30:22 UTC",
    "total_active": 39,
    "new_added": 0,
    "removed": 0,
    "buffered_ai": 0
  },
  {
    "time_utc": "2026-04-20 18:25:20 UTC",
    "total_active": 39,
    "new_added": 0,
    "removed": 0,
    "buffered_ai": 0
  },
  {
    "time_utc": "2026-04-20 18:20:22 UTC",
    "total_active": 39,
    "new_added": 0,
    "removed": 0,
    "buffered_ai": 0
  },
  {
    "time_utc": "2026-04-20 18:15:26 UTC",
    "total_active": 39,
    "new_added": 0,
    "removed": 0,
    "buffered_ai": 0
  },
  {
    "time_utc": "2026-04-20 18:10:23 UTC",
    "total_active": 39,
    "new_added": 0,
    "removed": 0,
    "buffered_ai": 0
  },
  {
    "time_utc": "2026-04-20 18:05:21 UTC",
    "total_active": 39,
    "new_added": 0,
    "removed": 0,
    "buffered_ai": 0
  },
  {
    "time_utc": "2026-04-20 18:00:27 UTC",
    "total_active": 39,
    "new_added": 0,
    "removed": 0,
    "buffered_ai": 0
  },
  {
    "time_utc": "2026-04-20 17:55:19 UTC",
    "total_active": 39,
    "new_added": 0,
    "removed": 0,
    "buffered_ai": 0
  },
  {
    "time_utc": "2026-04-20 17:50:21 UTC",
    "total_active": 39,
    "new_added": 0,
    "removed": 0,
    "buffered_ai": 0
  },
  {
    "time_utc": "2026-04-20 17:45:23 UTC",
    "total_active": 39,
    "new_added": 0,
    "removed": 0,
    "buffered_ai": 0
  },
  {
    "time_utc": "2026-04-20 17:40:25 UTC",
    "total_active": 39,
    "new_added": 0,
    "removed": 0,
    "buffered_ai": 0
  },
  {
    "time_utc": "2026-04-20 17:35:22 UTC",
    "total_active": 39,
    "new_added": 0,
    "removed": 0,
    "buffered_ai": 0
  },
  {
    "time_utc": "2026-04-20 17:30:30 UTC",
    "total_active": 39,
    "new_added": 0,
    "removed": 0,
    "buffered_ai": 0
  },
  {
    "time_utc": "2026-04-20 17:25:25 UTC",
    "total_active": 39,
    "new_added": 0,
    "removed": 0,
    "buffered_ai": 0
  },
  {
    "time_utc": "2026-04-20 17:20:21 UTC",
    "total_active": 39,
    "new_added": 0,
    "removed": 0,
    "buffered_ai": 0
  },
  {
    "time_utc": "2026-04-20 17:15:24 UTC",
    "total_active": 39,
    "new_added": 0,
    "removed": 0,
    "buffered_ai": 0
  },
  {
    "time_utc": "2026-04-20 17:10:21 UTC",
    "total_active": 39,
    "new_added": 0,
    "removed": 0,
    "buffered_ai": 0
  },
  {
    "time_utc": "2026-04-20 17:05:28 UTC",
    "total_active": 39,
    "new_added": 0,
    "removed": 0,
    "buffered_ai": 0
  },
  {
    "time_utc": "2026-04-20 17:00:25 UTC",
    "total_active": 39,
    "new_added": 0,
    "removed": 0,
    "buffered_ai": 0
  },
  {
    "time_utc": "2026-04-20 16:55:20 UTC",
    "total_active": 39,
    "new_added": 0,
    "removed": 0,
    "buffered_ai": 0
  },
  {
    "time_utc": "2026-04-20 16:50:21 UTC",
    "total_active": 39,
    "new_added": 0,
    "removed": 0,
    "buffered_ai": 0
  },
  {
    "time_utc": "2026-04-20 16:45:19 UTC",
    "total_active": 39,
    "new_added": 0,
    "removed": 0,
    "buffered_ai": 0
  },
  {
    "time_utc": "2026-04-20 16:40:30 UTC",
    "total_active": 39,
    "new_added": 0,
    "removed": 0,
    "buffered_ai": 0
  },
  {
    "time_utc": "2026-04-20 16:35:21 UTC",
    "total_active": 39,
    "new_added": 0,
    "removed": 0,
    "buffered_ai": 0
  },
  {
    "time_utc": "2026-04-20 16:30:30 UTC",
    "total_active": 39,
    "new_added": 0,
    "removed": 0,
    "buffered_ai": 0
  },
  {
    "time_utc": "2026-04-20 16:25:20 UTC",
    "total_active": 39,
    "new_added": 0,
    "removed": 0,
    "buffered_ai": 0
  },
  {
    "time_utc": "2026-04-20 16:20:27 UTC",
    "total_active": 39,
    "new_added": 0,
    "removed": 0,
    "buffered_ai": 0
  },
  {
    "time_utc": "2026-04-20 16:15:29 UTC",
    "total_active": 39,
    "new_added": 0,
    "removed": 0,
    "buffered_ai": 0
  },
  {
    "time_utc": "2026-04-20 16:10:25 UTC",
    "total_active": 39,
    "new_added": 0,
    "removed": 0,
    "buffered_ai": 0
  },
  {
    "time_utc": "2026-04-20 16:05:20 UTC",
    "total_active": 39,
    "new_added": 0,
    "removed": 0,
    "buffered_ai": 0
  },
  {
    "time_utc": "2026-04-20 16:00:28 UTC",
    "total_active": 39,
    "new_added": 0,
    "removed": 0,
    "buffered_ai": 0
  },
  {
    "time_utc": "2026-04-20 15:55:20 UTC",
    "total_active": 39,
    "new_added": 0,
    "removed": 0,
    "buffered_ai": 0
  },
  {
    "time_utc": "2026-04-20 15:50:22 UTC",
    "total_active": 39,
    "new_added": 0,
    "removed": 0,
    "buffered_ai": 0
  },
  {
    "time_utc": "2026-04-20 15:45:27 UTC",
    "total_active": 39,
    "new_added": 0,
    "removed": 0,
    "buffered_ai": 0
  },
  {
    "time_utc": "2026-04-20 15:40:28 UTC",
    "total_active": 39,
    "new_added": 0,
    "removed": 0,
    "buffered_ai": 0
  },
  {
    "time_utc": "2026-04-20 15:35:23 UTC",
    "total_active": 39,
    "new_added": 0,
    "removed": 0,
    "buffered_ai": 0
  },
  {
    "time_utc": "2026-04-20 15:30:25 UTC",
    "total_active": 39,
    "new_added": 0,
    "removed": 0,
    "buffered_ai": 0
  },
  {
    "time_utc": "2026-04-20 15:25:24 UTC",
    "total_active": 39,
    "new_added": 0,
    "removed": 0,
    "buffered_ai": 0
  },
  {
    "time_utc": "2026-04-20 15:20:21 UTC",
    "total_active": 39,
    "new_added": 0,
    "removed": 0,
    "buffered_ai": 0
  },
  {
    "time_utc": "2026-04-20 15:15:24 UTC",
    "total_active": 39,
    "new_added": 0,
    "removed": 0,
    "buffered_ai": 0
  },
  {
    "time_utc": "2026-04-20 15:10:26 UTC",
    "total_active": 39,
    "new_added": 0,
    "removed": 0,
    "buffered_ai": 0
  },
  {
    "time_utc": "2026-04-20 15:05:24 UTC",
    "total_active": 39,
    "new_added": 0,
    "removed": 0,
    "buffered_ai": 0
  },
  {
    "time_utc": "2026-04-20 15:00:46 UTC",
    "total_active": 39,
    "new_added": 0,
    "removed": 0,
    "buffered_ai": 0
  },
  {
    "time_utc": "2026-04-20 14:55:23 UTC",
    "total_active": 39,
    "new_added": 0,
    "removed": 0,
    "buffered_ai": 0
  },
  {
    "time_utc": "2026-04-20 14:50:26 UTC",
    "total_active": 39,
    "new_added": 0,
    "removed": 0,
    "buffered_ai": 0
  },
  {
    "time_utc": "2026-04-20 14:45:23 UTC",
    "total_active": 39,
    "new_added": 0,
    "removed": 0,
    "buffered_ai": 0
  },
  {
    "time_utc": "2026-04-20 14:40:26 UTC",
    "total_active": 39,
    "new_added": 0,
    "removed": 0,
    "buffered_ai": 0
  },
  {
    "time_utc": "2026-04-20 14:35:26 UTC",
    "total_active": 39,
    "new_added": 0,
    "removed": 0,
    "buffered_ai": 0
  },
  {
    "time_utc": "2026-04-20 14:30:41 UTC",
    "total_active": 39,
    "new_added": 0,
    "removed": 0,
    "buffered_ai": 0
  },
  {
    "time_utc": "2026-04-20 14:25:27 UTC",
    "total_active": 39,
    "new_added": 0,
    "removed": 0,
    "buffered_ai": 0
  },
  {
    "time_utc": "2026-04-20 14:20:23 UTC",
    "total_active": 39,
    "new_added": 0,
    "removed": 0,
    "buffered_ai": 0
  },
  {
    "time_utc": "2026-04-20 14:15:23 UTC",
    "total_active": 39,
    "new_added": 0,
    "removed": 0,
    "buffered_ai": 0
  },
  {
    "time_utc": "2026-04-20 14:10:23 UTC",
    "total_active": 39,
    "new_added": 0,
    "removed": 0,
    "buffered_ai": 0
  },
  {
    "time_utc": "2026-04-20 14:05:25 UTC",
    "total_active": 39,
    "new_added": 0,
    "removed": 0,
    "buffered_ai": 0
  },
  {
    "time_utc": "2026-04-20 14:00:26 UTC",
    "total_active": 39,
    "new_added": 0,
    "removed": 0,
    "buffered_ai": 0
  },
  {
    "time_utc": "2026-04-20 13:55:19 UTC",
    "total_active": 39,
    "new_added": 0,
    "removed": 0,
    "buffered_ai": 0
  },
  {
    "time_utc": "2026-04-20 13:50:25 UTC",
    "total_active": 39,
    "new_added": 0,
    "removed": 0,
    "buffered_ai": 0
  },
  {
    "time_utc": "2026-04-20 13:45:25 UTC",
    "total_active": 39,
    "new_added": 0,
    "removed": 0,
    "buffered_ai": 0
  },
  {
    "time_utc": "2026-04-20 13:40:28 UTC",
    "total_active": 39,
    "new_added": 0,
    "removed": 0,
    "buffered_ai": 0
  },
  {
    "time_utc": "2026-04-20 13:35:19 UTC",
    "total_active": 39,
    "new_added": 0,
    "removed": 0,
    "buffered_ai": 0
  },
  {
    "time_utc": "2026-04-20 13:30:26 UTC",
    "total_active": 39,
    "new_added": 0,
    "removed": 0,
    "buffered_ai": 0
  },
  {
    "time_utc": "2026-04-20 13:25:21 UTC",
    "total_active": 39,
    "new_added": 0,
    "removed": 0,
    "buffered_ai": 0
  },
  {
    "time_utc": "2026-04-20 13:20:23 UTC",
    "total_active": 39,
    "new_added": 0,
    "removed": 0,
    "buffered_ai": 0
  },
  {
    "time_utc": "2026-04-20 13:15:25 UTC",
    "total_active": 39,
    "new_added": 0,
    "removed": 0,
    "buffered_ai": 0
  },
  {
    "time_utc": "2026-04-20 13:10:25 UTC",
    "total_active": 39,
    "new_added": 0,
    "removed": 0,
    "buffered_ai": 0
  },
  {
    "time_utc": "2026-04-20 13:05:22 UTC",
    "total_active": 39,
    "new_added": 0,
    "removed": 0,
    "buffered_ai": 0
  },
  {
    "time_utc": "2026-04-20 13:00:28 UTC",
    "total_active": 39,
    "new_added": 0,
    "removed": 0,
    "buffered_ai": 0
  },
  {
    "time_utc": "2026-04-20 12:55:20 UTC",
    "total_active": 39,
    "new_added": 0,
    "removed": 0,
    "buffered_ai": 0
  },
  {
    "time_utc": "2026-04-20 12:50:28 UTC",
    "total_active": 39,
    "new_added": 0,
    "removed": 0,
    "buffered_ai": 0
  },
  {
    "time_utc": "2026-04-20 12:45:22 UTC",
    "total_active": 39,
    "new_added": 0,
    "removed": 0,
    "buffered_ai": 0
  },
  {
    "time_utc": "2026-04-20 12:40:27 UTC",
    "total_active": 39,
    "new_added": 0,
    "removed": 0,
    "buffered_ai": 0
  },
  {
    "time_utc": "2026-04-20 12:35:20 UTC",
    "total_active": 39,
    "new_added": 0,
    "removed": 0,
    "buffered_ai": 0
  },
  {
    "time_utc": "2026-04-20 12:30:24 UTC",
    "total_active": 39,
    "new_added": 0,
    "removed": 0,
    "buffered_ai": 0
  },
  {
    "time_utc": "2026-04-20 12:25:26 UTC",
    "total_active": 39,
    "new_added": 0,
    "removed": 0,
    "buffered_ai": 0
  },
  {
    "time_utc": "2026-04-20 12:20:25 UTC",
    "total_active": 39,
    "new_added": 0,
    "removed": 0,
    "buffered_ai": 0
  },
  {
    "time_utc": "2026-04-20 12:15:20 UTC",
    "total_active": 39,
    "new_added": 0,
    "removed": 0,
    "buffered_ai": 0
  },
  {
    "time_utc": "2026-04-20 12:10:21 UTC",
    "total_active": 39,
    "new_added": 0,
    "removed": 0,
    "buffered_ai": 0
  },
  {
    "time_utc": "2026-04-20 12:05:20 UTC",
    "total_active": 39,
    "new_added": 0,
    "removed": 0,
    "buffered_ai": 0
  },
  {
    "time_utc": "2026-04-20 12:00:28 UTC",
    "total_active": 39,
    "new_added": 0,
    "removed": 0,
    "buffered_ai": 0
  },
  {
    "time_utc": "2026-04-20 11:55:21 UTC",
    "total_active": 39,
    "new_added": 0,
    "removed": 0,
    "buffered_ai": 0
  },
  {
    "time_utc": "2026-04-20 11:50:21 UTC",
    "total_active": 39,
    "new_added": 0,
    "removed": 0,
    "buffered_ai": 0
  },
  {
    "time_utc": "2026-04-20 11:45:19 UTC",
    "total_active": 39,
    "new_added": 0,
    "removed": 0,
    "buffered_ai": 0
  },
  {
    "time_utc": "2026-04-20 11:40:26 UTC",
    "total_active": 39,
    "new_added": 0,
    "removed": 0,
    "buffered_ai": 0
  },
  {
    "time_utc": "2026-04-20 11:35:24 UTC",
    "total_active": 39,
    "new_added": 0,
    "removed": 0,
    "buffered_ai": 0
  },
  {
    "time_utc": "2026-04-20 11:30:23 UTC",
    "total_active": 39,
    "new_added": 0,
    "removed": 0,
    "buffered_ai": 0
  },
  {
    "time_utc": "2026-04-20 11:25:25 UTC",
    "total_active": 39,
    "new_added": 0,
    "removed": 0,
    "buffered_ai": 0
  },
  {
    "time_utc": "2026-04-20 11:20:20 UTC",
    "total_active": 39,
    "new_added": 0,
    "removed": 0,
    "buffered_ai": 0
  },
  {
    "time_utc": "2026-04-20 11:15:24 UTC",
    "total_active": 39,
    "new_added": 0,
    "removed": 0,
    "buffered_ai": 0
  },
  {
    "time_utc": "2026-04-20 11:10:22 UTC",
    "total_active": 39,
    "new_added": 0,
    "removed": 0,
    "buffered_ai": 0
  },
  {
    "time_utc": "2026-04-20 11:05:24 UTC",
    "total_active": 39,
    "new_added": 0,
    "removed": 0,
    "buffered_ai": 0
  },
  {
    "time_utc": "2026-04-20 11:00:26 UTC",
    "total_active": 39,
    "new_added": 0,
    "removed": 0,
    "buffered_ai": 0
  },
  {
    "time_utc": "2026-04-20 10:55:22 UTC",
    "total_active": 39,
    "new_added": 1,
    "removed": 0,
    "buffered_ai": 0
  },
  {
    "time_utc": "2026-04-20 10:50:20 UTC",
    "total_active": 38,
    "new_added": 1,
    "removed": 1,
    "buffered_ai": 1
  },
  {
    "time_utc": "2026-04-20 10:45:18 UTC",
    "total_active": 38,
    "new_added": 0,
    "removed": 0,
    "buffered_ai": 0
  },
  {
    "time_utc": "2026-04-20 10:40:23 UTC",
    "total_active": 38,
    "new_added": 0,
    "removed": 0,
    "buffered_ai": 0
  },
  {
    "time_utc": "2026-04-20 10:35:26 UTC",
    "total_active": 38,
    "new_added": 0,
    "removed": 0,
    "buffered_ai": 0
  },
  {
    "time_utc": "2026-04-20 10:30:20 UTC",
    "total_active": 38,
    "new_added": 0,
    "removed": 0,
    "buffered_ai": 0
  },
  {
    "time_utc": "2026-04-20 10:25:29 UTC",
    "total_active": 38,
    "new_added": 0,
    "removed": 0,
    "buffered_ai": 0
  },
  {
    "time_utc": "2026-04-20 10:20:21 UTC",
    "total_active": 38,
    "new_added": 0,
    "removed": 0,
    "buffered_ai": 0
  },
  {
    "time_utc": "2026-04-20 10:15:22 UTC",
    "total_active": 38,
    "new_added": 0,
    "removed": 0,
    "buffered_ai": 0
  }
]